[
  {
    "id": 149,
    "registration_id": 3648,
    "person_id": null,
    "event_id": null,
    "description": "HKFA - You have registered for the course 8U6-06 (75.00 HKD), 35.00 HKD shipping fee, and 20.00 HKD administration fee",
    "amount": 130,
    "invoice_identification": "354346901",
    "invoice_number": "HKFA-3648",
    "invoice_date": "2022-06-23T03:06:04.000Z",
    "secret_key": "d652c47f5a7fd5fd30efa08965a26fc588b803b0",
    "status": "Accepted",
    "type": "registration",
    "payment_method": "AsiaPay",
    "accepted_employee": null,
    "accepted_date": null,
    "note": null,
    "metadata": null,
    "access_at": null,
    "url": "https://www.ezactive.com/hkfa_websocket/payment?invoice_id=149&email=thao@gmail.com&url=https%3A%2F%2Ftest.paydollar.com%2Fb2cDemo%2Feng%2Fpayment%2FpayForm.jsp%3FmerchantId%3D88156613%26amount%3D130%26orderRef%3DHKFA-3648%26currCode%3D344%26payType%3DN%26https%3A%2F%2Fwww.ezactive.com%2Fhkfa_staging%2Fserver%2Fclient%2Fpayment%2FsuccessfulPaymentAction%3Fkey%3Dd652c47f5a7fd5fd30efa08965a26fc588b803b0%26https%3A%2F%2Fwww.ezactive.com%2Fhkfa_staging%2Fserver%2Fclient%2Fpayment%2FcancelPaymentAction%3Fkey%3Dd652c47f5a7fd5fd30efa08965a26fc588b803b0"
  },
  {
    "id": 150,
    "registration_id": 3649,
    "person_id": null,
    "event_id": null,
    "description": "HKFA - You have registered for the course 1U6-08 (75.00 HKD), and 20.00 HKD administration fee",
    "amount": 95,
    "invoice_identification": "354347123",
    "invoice_number": "HKFA-3649",
    "invoice_date": "2022-06-23T03:06:05.000Z",
    "secret_key": "44309436d4f07ccab60720b7907b13f2b5190080",
    "status": "Accepted",
    "type": "registration",
    "payment_method": "AsiaPay",
    "accepted_employee": null,
    "accepted_date": null,
    "note": null,
    "metadata": null,
    "access_at": null,
    "url": "https://www.ezactive.com/hkfa_websocket/payment?invoice_id=150&email=thao@gmail.com&url=https%3A%2F%2Ftest.paydollar.com%2Fb2cDemo%2Feng%2Fpayment%2FpayForm.jsp%3FmerchantId%3D88156613%26amount%3D95%26orderRef%3DHKFA-3649%26currCode%3D344%26payType%3DN%26https%3A%2F%2Fwww.ezactive.com%2Fhkfa_staging%2Fserver%2Fclient%2Fpayment%2FsuccessfulPaymentAction%3Fkey%3D44309436d4f07ccab60720b7907b13f2b5190080%26https%3A%2F%2Fwww.ezactive.com%2Fhkfa_staging%2Fserver%2Fclient%2Fpayment%2FcancelPaymentAction%3Fkey%3D44309436d4f07ccab60720b7907b13f2b5190080"
  },
  {
    "id": 151,
    "registration_id": 3650,
    "person_id": null,
    "event_id": null,
    "description": "HKFA - You have registered for the course 3U8-02 (75.00 HKD), 35.00 HKD shipping fee, and 20.00 HKD administration fee",
    "amount": 130,
    "invoice_identification": "354346555",
    "invoice_number": "HKFA-3650",
    "invoice_date": "2022-06-23T03:06:06.000Z",
    "secret_key": "17d32e022297e9f62eb49ddd4461d79cd279f47c",
    "status": "Accepted",
    "type": "registration",
    "payment_method": "AsiaPay",
    "accepted_employee": null,
    "accepted_date": null,
    "note": null,
    "metadata": null,
    "access_at": null,
    "url": "https://www.ezactive.com/hkfa_websocket/payment?invoice_id=151&email=thao@gmail.com&url=https%3A%2F%2Ftest.paydollar.com%2Fb2cDemo%2Feng%2Fpayment%2FpayForm.jsp%3FmerchantId%3D88156613%26amount%3D130%26orderRef%3DHKFA-3650%26currCode%3D344%26payType%3DN%26https%3A%2F%2Fwww.ezactive.com%2Fhkfa_staging%2Fserver%2Fclient%2Fpayment%2FsuccessfulPaymentAction%3Fkey%3D17d32e022297e9f62eb49ddd4461d79cd279f47c%26https%3A%2F%2Fwww.ezactive.com%2Fhkfa_staging%2Fserver%2Fclient%2Fpayment%2FcancelPaymentAction%3Fkey%3D17d32e022297e9f62eb49ddd4461d79cd279f47c"
  },
  {
    "id": 153,
    "registration_id": 3652,
    "person_id": null,
    "event_id": null,
    "description": "HKFA - You have registered for the course 4U6-04 (75.00 HKD), 35.00 HKD shipping fee, and 20.00 HKD administration fee",
    "amount": 130,
    "invoice_identification": "354346812",
    "invoice_number": "HKFA-3652",
    "invoice_date": "2022-06-23T03:06:20.000Z",
    "secret_key": "0ea2a7073cc87948fb164257a432820b3ad464f8",
    "status": "Accepted",
    "type": "registration",
    "payment_method": "AsiaPay",
    "accepted_employee": null,
    "accepted_date": null,
    "note": null,
    "metadata": null,
    "access_at": null,
    "url": "https://www.ezactive.com/hkfa_websocket/payment?invoice_id=153&email=thao@gmail.com&url=https%3A%2F%2Ftest.paydollar.com%2Fb2cDemo%2Feng%2Fpayment%2FpayForm.jsp%3FmerchantId%3D88156613%26amount%3D130%26orderRef%3DHKFA-3652%26currCode%3D344%26payType%3DN%26https%3A%2F%2Fwww.ezactive.com%2Fhkfa_staging%2Fserver%2Fclient%2Fpayment%2FsuccessfulPaymentAction%3Fkey%3D0ea2a7073cc87948fb164257a432820b3ad464f8%26https%3A%2F%2Fwww.ezactive.com%2Fhkfa_staging%2Fserver%2Fclient%2Fpayment%2FcancelPaymentAction%3Fkey%3D0ea2a7073cc87948fb164257a432820b3ad464f8"
  },
  {
    "id": 154,
    "registration_id": 3653,
    "person_id": null,
    "event_id": null,
    "description": "HKFA - You have registered for the course 5U8-03 (75.00 HKD), 35.00 HKD shipping fee, and 20.00 HKD administration fee",
    "amount": 130,
    "invoice_identification": "354346591",
    "invoice_number": "HKFA-3653",
    "invoice_date": "2022-06-23T03:06:20.000Z",
    "secret_key": "9909a4bf4d463cc39e7e6d8efb388a1d3e451d27",
    "status": "Accepted",
    "type": "registration",
    "payment_method": "AsiaPay",
    "accepted_employee": null,
    "accepted_date": null,
    "note": null,
    "metadata": null,
    "access_at": null,
    "url": "https://www.ezactive.com/hkfa_websocket/payment?invoice_id=154&email=thao@gmail.com&url=https%3A%2F%2Ftest.paydollar.com%2Fb2cDemo%2Feng%2Fpayment%2FpayForm.jsp%3FmerchantId%3D88156613%26amount%3D130%26orderRef%3DHKFA-3653%26currCode%3D344%26payType%3DN%26https%3A%2F%2Fwww.ezactive.com%2Fhkfa_staging%2Fserver%2Fclient%2Fpayment%2FsuccessfulPaymentAction%3Fkey%3D9909a4bf4d463cc39e7e6d8efb388a1d3e451d27%26https%3A%2F%2Fwww.ezactive.com%2Fhkfa_staging%2Fserver%2Fclient%2Fpayment%2FcancelPaymentAction%3Fkey%3D9909a4bf4d463cc39e7e6d8efb388a1d3e451d27"
  },
  {
    "id": 156,
    "registration_id": 3655,
    "person_id": null,
    "event_id": null,
    "description": "HKFA - You have registered for the course 8U8-05 (75.00 HKD), 35.00 HKD shipping fee, and 20.00 HKD administration fee",
    "amount": 130,
    "invoice_identification": "354346639",
    "invoice_number": "HKFA-3655",
    "invoice_date": "2022-06-23T03:06:24.000Z",
    "secret_key": "e4544f4c70614df1fdae428481ddb71744879e16",
    "status": "Accepted",
    "type": "registration",
    "payment_method": "AsiaPay",
    "accepted_employee": null,
    "accepted_date": null,
    "note": null,
    "metadata": null,
    "access_at": null,
    "url": "https://www.ezactive.com/hkfa_websocket/payment?invoice_id=156&email=thao@gmail.com&url=https%3A%2F%2Ftest.paydollar.com%2Fb2cDemo%2Feng%2Fpayment%2FpayForm.jsp%3FmerchantId%3D88156613%26amount%3D130%26orderRef%3DHKFA-3655%26currCode%3D344%26payType%3DN%26https%3A%2F%2Fwww.ezactive.com%2Fhkfa_staging%2Fserver%2Fclient%2Fpayment%2FsuccessfulPaymentAction%3Fkey%3De4544f4c70614df1fdae428481ddb71744879e16%26https%3A%2F%2Fwww.ezactive.com%2Fhkfa_staging%2Fserver%2Fclient%2Fpayment%2FcancelPaymentAction%3Fkey%3De4544f4c70614df1fdae428481ddb71744879e16"
  },
  {
    "id": 157,
    "registration_id": 3656,
    "person_id": null,
    "event_id": null,
    "description": "HKFA - You have registered for the course 6U8-07 (75.00 HKD), 35.00 HKD shipping fee, and 20.00 HKD administration fee",
    "amount": 130,
    "invoice_identification": "354346727",
    "invoice_number": "HKFA-3656",
    "invoice_date": "2022-06-23T03:06:27.000Z",
    "secret_key": "f8e611f28ebdacfc2402a74c335737324b1df780",
    "status": "Accepted",
    "type": "registration",
    "payment_method": "AsiaPay",
    "accepted_employee": null,
    "accepted_date": null,
    "note": null,
    "metadata": null,
    "access_at": null,
    "url": "https://www.ezactive.com/hkfa_websocket/payment?invoice_id=157&email=thao@gmail.com&url=https%3A%2F%2Ftest.paydollar.com%2Fb2cDemo%2Feng%2Fpayment%2FpayForm.jsp%3FmerchantId%3D88156613%26amount%3D130%26orderRef%3DHKFA-3656%26currCode%3D344%26payType%3DN%26https%3A%2F%2Fwww.ezactive.com%2Fhkfa_staging%2Fserver%2Fclient%2Fpayment%2FsuccessfulPaymentAction%3Fkey%3Df8e611f28ebdacfc2402a74c335737324b1df780%26https%3A%2F%2Fwww.ezactive.com%2Fhkfa_staging%2Fserver%2Fclient%2Fpayment%2FcancelPaymentAction%3Fkey%3Df8e611f28ebdacfc2402a74c335737324b1df780"
  },
  {
    "id": 158,
    "registration_id": 3657,
    "person_id": null,
    "event_id": null,
    "description": "HKFA - You have registered for the course 8U8-05 (75.00 HKD), and 20.00 HKD administration fee",
    "amount": 95,
    "invoice_identification": "354346638",
    "invoice_number": "HKFA-3657",
    "invoice_date": "2022-06-23T03:06:28.000Z",
    "secret_key": "64e8002c6f7731c7f103f1c3a1882c34a5866379",
    "status": "Accepted",
    "type": "registration",
    "payment_method": "AsiaPay",
    "accepted_employee": null,
    "accepted_date": null,
    "note": null,
    "metadata": null,
    "access_at": null,
    "url": "https://www.ezactive.com/hkfa_websocket/payment?invoice_id=158&email=thao@gmail.com&url=https%3A%2F%2Ftest.paydollar.com%2Fb2cDemo%2Feng%2Fpayment%2FpayForm.jsp%3FmerchantId%3D88156613%26amount%3D95%26orderRef%3DHKFA-3657%26currCode%3D344%26payType%3DN%26https%3A%2F%2Fwww.ezactive.com%2Fhkfa_staging%2Fserver%2Fclient%2Fpayment%2FsuccessfulPaymentAction%3Fkey%3D64e8002c6f7731c7f103f1c3a1882c34a5866379%26https%3A%2F%2Fwww.ezactive.com%2Fhkfa_staging%2Fserver%2Fclient%2Fpayment%2FcancelPaymentAction%3Fkey%3D64e8002c6f7731c7f103f1c3a1882c34a5866379"
  },
  {
    "id": 159,
    "registration_id": 3658,
    "person_id": null,
    "event_id": null,
    "description": "HKFA - You have registered for the course 3U10-06 (75.00 HKD), 35.00 HKD shipping fee, and 20.00 HKD administration fee",
    "amount": 130,
    "invoice_identification": "354346957",
    "invoice_number": "HKFA-3658",
    "invoice_date": "2022-06-23T03:06:38.000Z",
    "secret_key": "e1f988f50db18b2e68dbacb66733ffc932e0b0fb",
    "status": "Accepted",
    "type": "registration",
    "payment_method": "AsiaPay",
    "accepted_employee": null,
    "accepted_date": null,
    "note": null,
    "metadata": null,
    "access_at": null,
    "url": "https://www.ezactive.com/hkfa_websocket/payment?invoice_id=159&email=thao@gmail.com&url=https%3A%2F%2Ftest.paydollar.com%2Fb2cDemo%2Feng%2Fpayment%2FpayForm.jsp%3FmerchantId%3D88156613%26amount%3D130%26orderRef%3DHKFA-3658%26currCode%3D344%26payType%3DN%26https%3A%2F%2Fwww.ezactive.com%2Fhkfa_staging%2Fserver%2Fclient%2Fpayment%2FsuccessfulPaymentAction%3Fkey%3De1f988f50db18b2e68dbacb66733ffc932e0b0fb%26https%3A%2F%2Fwww.ezactive.com%2Fhkfa_staging%2Fserver%2Fclient%2Fpayment%2FcancelPaymentAction%3Fkey%3De1f988f50db18b2e68dbacb66733ffc932e0b0fb"
  },
  {
    "id": 160,
    "registration_id": 3659,
    "person_id": null,
    "event_id": null,
    "description": "HKFA - You have registered for the course 7U8-03 (75.00 HKD), 35.00 HKD shipping fee, and 20.00 HKD administration fee",
    "amount": 130,
    "invoice_identification": "354347002",
    "invoice_number": "HKFA-3659",
    "invoice_date": "2022-06-23T03:06:50.000Z",
    "secret_key": "1dfc8460b3e69e0d19ba0d83d4efc663c7bd9376",
    "status": "Accepted",
    "type": "registration",
    "payment_method": "AsiaPay",
    "accepted_employee": null,
    "accepted_date": null,
    "note": null,
    "metadata": null,
    "access_at": null,
    "url": "https://www.ezactive.com/hkfa_websocket/payment?invoice_id=160&email=thao@gmail.com&url=https%3A%2F%2Ftest.paydollar.com%2Fb2cDemo%2Feng%2Fpayment%2FpayForm.jsp%3FmerchantId%3D88156613%26amount%3D130%26orderRef%3DHKFA-3659%26currCode%3D344%26payType%3DN%26https%3A%2F%2Fwww.ezactive.com%2Fhkfa_staging%2Fserver%2Fclient%2Fpayment%2FsuccessfulPaymentAction%3Fkey%3D1dfc8460b3e69e0d19ba0d83d4efc663c7bd9376%26https%3A%2F%2Fwww.ezactive.com%2Fhkfa_staging%2Fserver%2Fclient%2Fpayment%2FcancelPaymentAction%3Fkey%3D1dfc8460b3e69e0d19ba0d83d4efc663c7bd9376"
  },
  {
    "id": 161,
    "registration_id": 3660,
    "person_id": null,
    "event_id": null,
    "description": "HKFA - You have registered for the course 2U6-08 (75.00 HKD), and 20.00 HKD administration fee",
    "amount": 95,
    "invoice_identification": "354346907",
    "invoice_number": "HKFA-3660",
    "invoice_date": "2022-06-23T03:06:52.000Z",
    "secret_key": "fc799e42632e9bfc079301e6cf83575ef5c842e1",
    "status": "Accepted",
    "type": "registration",
    "payment_method": "AsiaPay",
    "accepted_employee": null,
    "accepted_date": null,
    "note": null,
    "metadata": null,
    "access_at": null,
    "url": "https://www.ezactive.com/hkfa_websocket/payment?invoice_id=161&email=thao@gmail.com&url=https%3A%2F%2Ftest.paydollar.com%2Fb2cDemo%2Feng%2Fpayment%2FpayForm.jsp%3FmerchantId%3D88156613%26amount%3D95%26orderRef%3DHKFA-3660%26currCode%3D344%26payType%3DN%26https%3A%2F%2Fwww.ezactive.com%2Fhkfa_staging%2Fserver%2Fclient%2Fpayment%2FsuccessfulPaymentAction%3Fkey%3Dfc799e42632e9bfc079301e6cf83575ef5c842e1%26https%3A%2F%2Fwww.ezactive.com%2Fhkfa_staging%2Fserver%2Fclient%2Fpayment%2FcancelPaymentAction%3Fkey%3Dfc799e42632e9bfc079301e6cf83575ef5c842e1"
  },
  {
    "id": 162,
    "registration_id": 3661,
    "person_id": null,
    "event_id": null,
    "description": "HKFA - You have registered for the course 8U8-06 (75.00 HKD), 35.00 HKD shipping fee, and 20.00 HKD administration fee",
    "amount": 130,
    "invoice_identification": "354347218",
    "invoice_number": "HKFA-3661",
    "invoice_date": "2022-06-23T03:06:56.000Z",
    "secret_key": "3c466febb4ae4e95e85892aaf95c51570899d9a8",
    "status": "Accepted",
    "type": "registration",
    "payment_method": "AsiaPay",
    "accepted_employee": null,
    "accepted_date": null,
    "note": null,
    "metadata": null,
    "access_at": null,
    "url": "https://www.ezactive.com/hkfa_websocket/payment?invoice_id=162&email=thao@gmail.com&url=https%3A%2F%2Ftest.paydollar.com%2Fb2cDemo%2Feng%2Fpayment%2FpayForm.jsp%3FmerchantId%3D88156613%26amount%3D130%26orderRef%3DHKFA-3661%26currCode%3D344%26payType%3DN%26https%3A%2F%2Fwww.ezactive.com%2Fhkfa_staging%2Fserver%2Fclient%2Fpayment%2FsuccessfulPaymentAction%3Fkey%3D3c466febb4ae4e95e85892aaf95c51570899d9a8%26https%3A%2F%2Fwww.ezactive.com%2Fhkfa_staging%2Fserver%2Fclient%2Fpayment%2FcancelPaymentAction%3Fkey%3D3c466febb4ae4e95e85892aaf95c51570899d9a8"
  },
  {
    "id": 163,
    "registration_id": 3662,
    "person_id": null,
    "event_id": null,
    "description": "HKFA - You have registered for the course 4U12-01 (75.00 HKD), and 20.00 HKD administration fee",
    "amount": 95,
    "invoice_identification": "354347373",
    "invoice_number": "HKFA-3662",
    "invoice_date": "2022-06-23T03:06:58.000Z",
    "secret_key": "9694347b0bda3a921d2550e33f2ccbd607b11cb4",
    "status": "Accepted",
    "type": "registration",
    "payment_method": "AsiaPay",
    "accepted_employee": null,
    "accepted_date": null,
    "note": null,
    "metadata": null,
    "access_at": null,
    "url": "https://www.ezactive.com/hkfa_websocket/payment?invoice_id=163&email=thao@gmail.com&url=https%3A%2F%2Ftest.paydollar.com%2Fb2cDemo%2Feng%2Fpayment%2FpayForm.jsp%3FmerchantId%3D88156613%26amount%3D95%26orderRef%3DHKFA-3662%26currCode%3D344%26payType%3DN%26https%3A%2F%2Fwww.ezactive.com%2Fhkfa_staging%2Fserver%2Fclient%2Fpayment%2FsuccessfulPaymentAction%3Fkey%3D9694347b0bda3a921d2550e33f2ccbd607b11cb4%26https%3A%2F%2Fwww.ezactive.com%2Fhkfa_staging%2Fserver%2Fclient%2Fpayment%2FcancelPaymentAction%3Fkey%3D9694347b0bda3a921d2550e33f2ccbd607b11cb4"
  },
  {
    "id": 164,
    "registration_id": 3663,
    "person_id": null,
    "event_id": null,
    "description": "HKFA - You have registered for the course 8U10-03 (75.00 HKD), 35.00 HKD shipping fee, and 20.00 HKD administration fee",
    "amount": 130,
    "invoice_identification": "354347939",
    "invoice_number": "HKFA-3663",
    "invoice_date": "2022-06-23T03:06:59.000Z",
    "secret_key": "bc5220406e4efa53fa313d48d5fa50056f2c5f84",
    "status": "Accepted",
    "type": "registration",
    "payment_method": "AsiaPay",
    "accepted_employee": null,
    "accepted_date": null,
    "note": null,
    "metadata": null,
    "access_at": null,
    "url": "https://www.ezactive.com/hkfa_websocket/payment?invoice_id=164&email=thao@gmail.com&url=https%3A%2F%2Ftest.paydollar.com%2Fb2cDemo%2Feng%2Fpayment%2FpayForm.jsp%3FmerchantId%3D88156613%26amount%3D130%26orderRef%3DHKFA-3663%26currCode%3D344%26payType%3DN%26https%3A%2F%2Fwww.ezactive.com%2Fhkfa_staging%2Fserver%2Fclient%2Fpayment%2FsuccessfulPaymentAction%3Fkey%3Dbc5220406e4efa53fa313d48d5fa50056f2c5f84%26https%3A%2F%2Fwww.ezactive.com%2Fhkfa_staging%2Fserver%2Fclient%2Fpayment%2FcancelPaymentAction%3Fkey%3Dbc5220406e4efa53fa313d48d5fa50056f2c5f84"
  },
  {
    "id": 165,
    "registration_id": 3664,
    "person_id": null,
    "event_id": null,
    "description": "HKFA - You have registered for the course 4U8-08 (75.00 HKD), and 20.00 HKD administration fee",
    "amount": 95,
    "invoice_identification": "354347381",
    "invoice_number": "HKFA-3664",
    "invoice_date": "2022-06-23T03:07:06.000Z",
    "secret_key": "4ec5abe457e7216dbfa223cd64db6c0b4a3ecbd0",
    "status": "Accepted",
    "type": "registration",
    "payment_method": "AsiaPay",
    "accepted_employee": null,
    "accepted_date": null,
    "note": null,
    "metadata": null,
    "access_at": null,
    "url": "https://www.ezactive.com/hkfa_websocket/payment?invoice_id=165&email=thao@gmail.com&url=https%3A%2F%2Ftest.paydollar.com%2Fb2cDemo%2Feng%2Fpayment%2FpayForm.jsp%3FmerchantId%3D88156613%26amount%3D95%26orderRef%3DHKFA-3664%26currCode%3D344%26payType%3DN%26https%3A%2F%2Fwww.ezactive.com%2Fhkfa_staging%2Fserver%2Fclient%2Fpayment%2FsuccessfulPaymentAction%3Fkey%3D4ec5abe457e7216dbfa223cd64db6c0b4a3ecbd0%26https%3A%2F%2Fwww.ezactive.com%2Fhkfa_staging%2Fserver%2Fclient%2Fpayment%2FcancelPaymentAction%3Fkey%3D4ec5abe457e7216dbfa223cd64db6c0b4a3ecbd0"
  },
  {
    "id": 166,
    "registration_id": 3665,
    "person_id": null,
    "event_id": null,
    "description": "HKFA - You have registered for the course 6U8-08 (75.00 HKD), and 20.00 HKD administration fee",
    "amount": 95,
    "invoice_identification": "354347510",
    "invoice_number": "HKFA-3665",
    "invoice_date": "2022-06-23T03:07:09.000Z",
    "secret_key": "4f957e9ef512c5302988a3ebb72412cba3e2f339",
    "status": "Accepted",
    "type": "registration",
    "payment_method": "AsiaPay",
    "accepted_employee": null,
    "accepted_date": null,
    "note": null,
    "metadata": null,
    "access_at": null,
    "url": "https://www.ezactive.com/hkfa_websocket/payment?invoice_id=166&email=thao@gmail.com&url=https%3A%2F%2Ftest.paydollar.com%2Fb2cDemo%2Feng%2Fpayment%2FpayForm.jsp%3FmerchantId%3D88156613%26amount%3D95%26orderRef%3DHKFA-3665%26currCode%3D344%26payType%3DN%26https%3A%2F%2Fwww.ezactive.com%2Fhkfa_staging%2Fserver%2Fclient%2Fpayment%2FsuccessfulPaymentAction%3Fkey%3D4f957e9ef512c5302988a3ebb72412cba3e2f339%26https%3A%2F%2Fwww.ezactive.com%2Fhkfa_staging%2Fserver%2Fclient%2Fpayment%2FcancelPaymentAction%3Fkey%3D4f957e9ef512c5302988a3ebb72412cba3e2f339"
  },
  {
    "id": 167,
    "registration_id": 3666,
    "person_id": null,
    "event_id": null,
    "description": "HKFA - You have registered for the course 8U10-04 (75.00 HKD), 35.00 HKD shipping fee, and 20.00 HKD administration fee",
    "amount": 130,
    "invoice_identification": "354346874",
    "invoice_number": "HKFA-3666",
    "invoice_date": "2022-06-23T03:07:12.000Z",
    "secret_key": "de37070d1288de78b6a91c68a9ef1e5c3e492f2c",
    "status": "Accepted",
    "type": "registration",
    "payment_method": "AsiaPay",
    "accepted_employee": null,
    "accepted_date": null,
    "note": null,
    "metadata": null,
    "access_at": null,
    "url": "https://www.ezactive.com/hkfa_websocket/payment?invoice_id=167&email=thao@gmail.com&url=https%3A%2F%2Ftest.paydollar.com%2Fb2cDemo%2Feng%2Fpayment%2FpayForm.jsp%3FmerchantId%3D88156613%26amount%3D130%26orderRef%3DHKFA-3666%26currCode%3D344%26payType%3DN%26https%3A%2F%2Fwww.ezactive.com%2Fhkfa_staging%2Fserver%2Fclient%2Fpayment%2FsuccessfulPaymentAction%3Fkey%3Dde37070d1288de78b6a91c68a9ef1e5c3e492f2c%26https%3A%2F%2Fwww.ezactive.com%2Fhkfa_staging%2Fserver%2Fclient%2Fpayment%2FcancelPaymentAction%3Fkey%3Dde37070d1288de78b6a91c68a9ef1e5c3e492f2c"
  },
  {
    "id": 168,
    "registration_id": 3667,
    "person_id": null,
    "event_id": null,
    "description": "HKFA - You have registered for the course 5U14-01 (75.00 HKD), 35.00 HKD shipping fee, and 20.00 HKD administration fee",
    "amount": 130,
    "invoice_identification": "354346793",
    "invoice_number": "HKFA-3667",
    "invoice_date": "2022-06-23T03:07:12.000Z",
    "secret_key": "94789cb5537f47ff3e76548fda1cbb42d74738a3",
    "status": "Accepted",
    "type": "registration",
    "payment_method": "AsiaPay",
    "accepted_employee": null,
    "accepted_date": null,
    "note": null,
    "metadata": null,
    "access_at": null,
    "url": "https://www.ezactive.com/hkfa_websocket/payment?invoice_id=168&email=thao@gmail.com&url=https%3A%2F%2Ftest.paydollar.com%2Fb2cDemo%2Feng%2Fpayment%2FpayForm.jsp%3FmerchantId%3D88156613%26amount%3D130%26orderRef%3DHKFA-3667%26currCode%3D344%26payType%3DN%26https%3A%2F%2Fwww.ezactive.com%2Fhkfa_staging%2Fserver%2Fclient%2Fpayment%2FsuccessfulPaymentAction%3Fkey%3D94789cb5537f47ff3e76548fda1cbb42d74738a3%26https%3A%2F%2Fwww.ezactive.com%2Fhkfa_staging%2Fserver%2Fclient%2Fpayment%2FcancelPaymentAction%3Fkey%3D94789cb5537f47ff3e76548fda1cbb42d74738a3"
  },
  {
    "id": 169,
    "registration_id": 3668,
    "person_id": null,
    "event_id": null,
    "description": "HKFA - You have registered for the course 8U6-05 (75.00 HKD), 35.00 HKD shipping fee, and 20.00 HKD administration fee",
    "amount": 130,
    "invoice_identification": "354346697",
    "invoice_number": "HKFA-3668",
    "invoice_date": "2022-06-23T03:07:12.000Z",
    "secret_key": "7172f569c9e5c94ec021e468797e1839f1242928",
    "status": "Accepted",
    "type": "registration",
    "payment_method": "AsiaPay",
    "accepted_employee": null,
    "accepted_date": null,
    "note": null,
    "metadata": null,
    "access_at": null,
    "url": "https://www.ezactive.com/hkfa_websocket/payment?invoice_id=169&email=thao@gmail.com&url=https%3A%2F%2Ftest.paydollar.com%2Fb2cDemo%2Feng%2Fpayment%2FpayForm.jsp%3FmerchantId%3D88156613%26amount%3D130%26orderRef%3DHKFA-3668%26currCode%3D344%26payType%3DN%26https%3A%2F%2Fwww.ezactive.com%2Fhkfa_staging%2Fserver%2Fclient%2Fpayment%2FsuccessfulPaymentAction%3Fkey%3D7172f569c9e5c94ec021e468797e1839f1242928%26https%3A%2F%2Fwww.ezactive.com%2Fhkfa_staging%2Fserver%2Fclient%2Fpayment%2FcancelPaymentAction%3Fkey%3D7172f569c9e5c94ec021e468797e1839f1242928"
  },
  {
    "id": 170,
    "registration_id": 3669,
    "person_id": null,
    "event_id": null,
    "description": "HKFA - You have registered for the course 8U8-03 (75.00 HKD), 35.00 HKD shipping fee, and 20.00 HKD administration fee",
    "amount": 130,
    "invoice_identification": "354348057",
    "invoice_number": "HKFA-3669",
    "invoice_date": "2022-06-23T03:07:12.000Z",
    "secret_key": "4d9c7310569aafc5177d1881936a778eceb0003a",
    "status": "Accepted",
    "type": "registration",
    "payment_method": "AsiaPay",
    "accepted_employee": null,
    "accepted_date": null,
    "note": null,
    "metadata": null,
    "access_at": null,
    "url": "https://www.ezactive.com/hkfa_websocket/payment?invoice_id=170&email=thao@gmail.com&url=https%3A%2F%2Ftest.paydollar.com%2Fb2cDemo%2Feng%2Fpayment%2FpayForm.jsp%3FmerchantId%3D88156613%26amount%3D130%26orderRef%3DHKFA-3669%26currCode%3D344%26payType%3DN%26https%3A%2F%2Fwww.ezactive.com%2Fhkfa_staging%2Fserver%2Fclient%2Fpayment%2FsuccessfulPaymentAction%3Fkey%3D4d9c7310569aafc5177d1881936a778eceb0003a%26https%3A%2F%2Fwww.ezactive.com%2Fhkfa_staging%2Fserver%2Fclient%2Fpayment%2FcancelPaymentAction%3Fkey%3D4d9c7310569aafc5177d1881936a778eceb0003a"
  }
]